identifier_tools/__init__.py
identifier_tools/formats.py
identifier_tools/formats_constants.py
identifier_tools/ico.py
identifier_tools/iso.py
identifier_tools/lei.py
identifier_tools/mappers.py
identifier_tools/nic.py
identifier_tools/tests/__init__.py
identifier_tools/tests/test_de_trd_rgstr_cd_xjustiz_id.py
identifier_tools/tests/test_formats.py
identifier_tools/tests/test_ico.py
identifier_tools/tests/test_iso.py
identifier_tools/tests/test_lei.py
identifier_tools/tests/test_mappers.py
identifier_tools/tests/test_nic.py
identifier_tools/tests/utils.py
identifier_tools-2.7.0.dist-info/LICENSE
identifier_tools-2.7.0.dist-info/METADATA
identifier_tools-2.7.0.dist-info/WHEEL
identifier_tools-2.7.0.dist-info/top_level.txt
identifier_tools-2.7.0.dist-info/RECORD
