Metadata-Version: 2.1
Name: identifier-tools
Version: 2.7.0
Summary: Library that helps working with different identifier types.
Home-page: https://github.com/ricco386/identifier-tools
Author: Richard Kellner
Author-email: richard.kellner@nbs.sk
License: MIT
License-File: LICENSE
Requires-Dist: postal-codes-tools (>1.1.0)
Requires-Dist: postal-codes-tools (<1.2)
